allocator/__init__.py
allocator/api/__init__.py
allocator/api/cluster.py
allocator/api/distance.py
allocator/api/route.py
allocator/api/types.py
allocator/cli/__init__.py
allocator/cli/cluster_cmd.py
allocator/cli/main.py
allocator/cli/route_cmd.py
allocator/core/__init__.py
allocator/core/algorithms.py
allocator/core/routing.py
allocator/distances/__init__.py
allocator/distances/euclidean.py
allocator/distances/external_apis.py
allocator/distances/factory.py
allocator/distances/haversine.py
allocator/io/__init__.py
allocator/io/data_handler.py
allocator/py.typed
allocator/utils.py
allocator/viz/__init__.py
allocator/viz/plotting.py
allocator-1.1.0.dist-info/WHEEL
allocator-1.1.0.dist-info/entry_points.txt
allocator-1.1.0.dist-info/METADATA
allocator-1.1.0.dist-info/RECORD
