Metadata-Version: 2.4
Name: allocator
Version: 1.1.0
Summary: Modern Python package for geographic task allocation, clustering, and routing optimization
Keywords: geographic,allocation,clustering,routing,optimization,tsp,kmeans,geospatial,logistics,shortest-path
Author: Suriyan Laohaprapanon, Gaurav Sood
Author-email: Suriyan Laohaprapanon <suriyant@gmail.com>, Gaurav Sood <gsood07@gmail.com>
License-Expression: MIT
Classifier: Development Status :: 5 - Production/Stable
Classifier: Intended Audience :: Developers
Classifier: Intended Audience :: Science/Research
Classifier: Operating System :: OS Independent
Classifier: Programming Language :: Python :: 3
Classifier: Programming Language :: Python :: 3.11
Classifier: Programming Language :: Python :: 3.12
Classifier: Programming Language :: Python :: 3.13
Classifier: Programming Language :: Python :: 3 :: Only
Classifier: Topic :: Scientific/Engineering :: Information Analysis
Classifier: Topic :: Scientific/Engineering :: GIS
Classifier: Topic :: Software Development :: Libraries :: Python Modules
Classifier: Topic :: Utilities
Classifier: Typing :: Typed
Requires-Dist: pandas>=2.0.0
Requires-Dist: numpy>=1.24.0
Requires-Dist: utm>=0.7.0
Requires-Dist: haversine>=2.8.0
Requires-Dist: networkx>=3.0
Requires-Dist: click>=8.0.0
Requires-Dist: rich>=13.0.0
Requires-Dist: requests>=2.28.0
Requires-Dist: googlemaps>=4.6.0
Requires-Dist: ortools>=9.5.0
Requires-Dist: matplotlib>=3.6.0
Requires-Dist: seaborn>=0.13.2
Requires-Dist: christofides>=1.0.0 ; extra == 'algorithms'
Requires-Dist: scikit-learn>=1.3.0 ; extra == 'algorithms'
Requires-Dist: allocator[algorithms,geo] ; extra == 'all'
Requires-Dist: allocator[all,dev,test,docs] ; extra == 'complete'
Requires-Dist: ruff>=0.1.0 ; extra == 'dev'
Requires-Dist: mypy>=1.5.0 ; extra == 'dev'
Requires-Dist: black>=23.0.0 ; extra == 'dev'
Requires-Dist: isort>=5.12.0 ; extra == 'dev'
Requires-Dist: pre-commit>=3.0.0 ; extra == 'dev'
Requires-Dist: sphinx>=7.0.0 ; extra == 'docs'
Requires-Dist: furo>=2023.9.10 ; extra == 'docs'
Requires-Dist: myst-parser>=2.0.0 ; extra == 'docs'
Requires-Dist: linkify-it-py>=2.0.0 ; extra == 'docs'
Requires-Dist: sphinx-autodoc-typehints>=1.24.0 ; extra == 'docs'
Requires-Dist: sphinx-design>=0.5.0 ; extra == 'docs'
Requires-Dist: folium>=0.14.0 ; extra == 'geo'
Requires-Dist: polyline>=2.0.0 ; extra == 'geo'
Requires-Dist: pytest>=7.4.0 ; extra == 'test'
Requires-Dist: pytest-cov>=4.1.0 ; extra == 'test'
Requires-Dist: pytest-xdist>=3.3.0 ; extra == 'test'
Requires-Dist: coverage>=7.2.0 ; extra == 'test'
Requires-Dist: hypothesis>=6.82.0 ; extra == 'test'
Maintainer: Gaurav Sood
Maintainer-email: Gaurav Sood <gsood07@gmail.com>
Requires-Python: >=3.11
Project-URL: Bug Reports, https://github.com/geosensing/allocator/issues
Project-URL: Changelog, https://github.com/geosensing/allocator/blob/main/CHANGELOG.md
Project-URL: Documentation, https://geosensing.github.io/allocator/
Project-URL: Homepage, https://github.com/geosensing/allocator
Project-URL: Repository, https://github.com/geosensing/allocator.git
Project-URL: Source Code, https://github.com/geosensing/allocator
Provides-Extra: algorithms
Provides-Extra: all
Provides-Extra: complete
Provides-Extra: dev
Provides-Extra: docs
Provides-Extra: geo
Provides-Extra: test
